{"name":"choose_menu_breakfast_day","testCaseName":"com.frolova.features.createmenu.CreateMenuDayStory","testSteps":[{"number":1,"description":"Is the menu page","duration":9594,"startTime":1430989802206,"screenshots":[{"screenshot":"20ebc14c9b1bea80c5c3aeab6dd9b707_NONE.png"},{"screenshot":"0d9430b40a854b3e24bab57a84684c76_NONE.png"}],"result":"SUCCESS"},{"number":2,"description":"Open create menu breakfast day","duration":8390,"startTime":1430989811804,"screenshots":[{"screenshot":"837b74d58b6f631df2ba1d35699f369d_NONE.png"}],"result":"SUCCESS"}],"userStory":{"id":"com.frolova.features.createmenu.CreateMenuDayStory","storyName":"Create menu day story","storyClassName":"com.frolova.features.createmenu.CreateMenuDayStory","path":"com.frolova.features.createmenu","type":"story"},"title":"Choose menu breakfast day","tags":[{"name":"Create menu day story","type":"story"},{"name":"Createmenu","type":"feature"}],"startTime":1430989802196,"duration":18021,"driver":"firefox","manual":false,"result":"SUCCESS"}